norm_tree/__init__.py
norm_tree/test.py
norm_tree-0.0.0.dist-info/METADATA
norm_tree-0.0.0.dist-info/WHEEL
norm_tree-0.0.0.dist-info/top_level.txt
norm_tree-0.0.0.dist-info/RECORD
